SortFile/__init__.py
SortFile/main.py
SortFile-1.0.0.dist-info/LICENSE
SortFile-1.0.0.dist-info/METADATA
SortFile-1.0.0.dist-info/WHEEL
SortFile-1.0.0.dist-info/entry_points.txt
SortFile-1.0.0.dist-info/top_level.txt
SortFile-1.0.0.dist-info/RECORD
