Metadata-Version: 2.1
Name: SortFile
Version: 1.0.0
Summary: A package for sorting files based on a specified pattern.
Author: Wissam Al-Kahwaji
Author-email: Wissam Al-Kahwaji <wissamalkahwaji@gmail.com>
Project-URL: Homepage, https://github.com/wissam-al-kahwaji/SortFile
Project-URL: Bug Tracker, https://github.com/wissam-al-kahwaji/SortFile/issues
Keywords: python,Sort,SortFile,Sorting,Data
Classifier: Development Status :: 5 - Production/Stable
Classifier: Intended Audience :: Developers
Classifier: Intended Audience :: End Users/Desktop
Classifier: Programming Language :: Python :: 3
Classifier: License :: OSI Approved :: MIT License
Classifier: Operating System :: Microsoft :: Windows
Classifier: Operating System :: MacOS :: MacOS X
Classifier: Operating System :: POSIX :: Linux
Classifier: Operating System :: Unix
Requires-Python: >=3.7
License-File: LICENSE
